choicepy/__init__.py
choicepy-0.0.1a1.dist-info/LICENSE
choicepy-0.0.1a1.dist-info/METADATA
choicepy-0.0.1a1.dist-info/WHEEL
choicepy-0.0.1a1.dist-info/top_level.txt
choicepy-0.0.1a1.dist-info/RECORD
