Metadata-Version: 2.1
Name: choicepy
Version: 0.0.1a1
Summary: A package for social choice and voting
Home-page: https://github.com/seyhunsaral/choicepy
Author: Annika Hennes, Ali Seyhun Saral
Author-email: hennes@coll.mpg.de, saral@coll.mpg.de
License: MIT License
Platform: UNKNOWN
Requires-Python: >3.6.0
Requires-Dist: numpy (>=1.18.5)
